{
  "name": "TcEjerc",
  "fields": [
    {
      "fieldName": "clave",
      "fieldType": "String",
      "fieldValidateRules": ["required"]
    },
    {
      "fieldName": "valor",
      "fieldType": "Integer",
      "fieldValidateRules": ["required"]
    },
    {
      "fieldName": "fechaInicio",
      "fieldType": "Instant"
    },
    {
      "fieldName": "fechaFin",
      "fieldType": "Instant"
    },
    {
      "fieldName": "usuario",
      "fieldType": "String"
    }
  ],
  "relationships": [],
  "changelogDate": "20201220154614",
  "entityTableName": "tc_ejerc",
  "dto": "mapstruct",
  "pagination": "pagination",
  "service": "serviceClass",
  "jpaMetamodelFiltering": false,
  "fluentMethods": true,
  "readOnly": false,
  "embedded": false,
  "clientRootFolder": "",
  "applications": ["rfcrf"],
  "microserviceName": "servicios"
}
